terragraph/__init__.py
terragraph/cli.py
terragraph/core.py
terragraph/py.typed
terragraph-0.4.0.dist-info/AUTHORS.rst
terragraph-0.4.0.dist-info/LICENSE
terragraph-0.4.0.dist-info/METADATA
terragraph-0.4.0.dist-info/WHEEL
terragraph-0.4.0.dist-info/entry_points.txt
terragraph-0.4.0.dist-info/top_level.txt
terragraph-0.4.0.dist-info/RECORD
