Metadata-Version: 2.1
Name: terragraph
Version: 0.4.0
Summary: A package to help vizualise output from terraform graph as an svg file
Author-email: Chris Doyle <uk.chris.doyle+cdsre@gmail.com>
License: MIT license
Project-URL: Homepage, https://github.com/cdsre/terragraph
Keywords: terragraph
Classifier: Development Status :: 2 - Pre-Alpha
Classifier: Intended Audience :: Developers
Classifier: License :: OSI Approved :: MIT License
Classifier: Natural Language :: English
Classifier: Programming Language :: Python :: 3
Classifier: Programming Language :: Python :: 3.6
Classifier: Programming Language :: Python :: 3.7
Classifier: Programming Language :: Python :: 3.8
Requires-Python: >=3.9
License-File: LICENSE
License-File: AUTHORS.rst
Requires-Dist: Click >=7.0
Requires-Dist: pydot >=2.0.0
Provides-Extra: dev
Requires-Dist: pytest >=3 ; extra == 'dev'
Requires-Dist: pylint ; extra == 'dev'
Requires-Dist: black ; extra == 'dev'
Requires-Dist: mypy ; extra == 'dev'
Requires-Dist: sphinx ; extra == 'dev'
Requires-Dist: sphinx-rtd-theme ; extra == 'dev'
Requires-Dist: sphinx-click ; extra == 'dev'
Requires-Dist: pylint-pytest ; extra == 'dev'
Requires-Dist: tox ; extra == 'dev'
